cubicweb_editorjs/__init__.py
cubicweb_editorjs/__pkginfo__.py
cubicweb_editorjs/data/cubes.editorjs.js
cubicweb_editorjs/i18n/en.po
cubicweb_editorjs/i18n/es.po
cubicweb_editorjs/i18n/fr.po
cubicweb_editorjs-0.3.0.dist-info/METADATA
cubicweb_editorjs-0.3.0.dist-info/WHEEL
cubicweb_editorjs-0.3.0.dist-info/entry_points.txt
cubicweb_editorjs-0.3.0.dist-info/top_level.txt
cubicweb_editorjs-0.3.0.dist-info/RECORD
